<?xml version="1.0" encoding="UTF-8"?>
<theorem xmlns="Theorem"
         xmlns:xsi="http://www.w3.org/2001/XMLSchema-instance"
         type="Proposition"
         id="Thm_DirectionAngleCompute"
         xsi:schemaLocation="Theorem file:/C:/xampp/htdocs/moodle/mod/msm/XSLTdocuments/Theorem.xsd">
   <caption>Computing Direction Angles</caption>
   <associate type="Example">
      <showme.pack.ref showmePackID="Exa_DirectionAngles"/>
      <info>
         <para>
            <para.body>Examples of direction angles</para.body>
         </para>
      </info>
   </associate>
   <statement.theorem>
      <para>
         <para.body>The <math>
               <latex>i</latex>
            </math>-th direction angle of a vector <math>
               <latex>\mathbf{x} = (x_1,\dots ,x_n)</latex>
            </math> in <math>
               <latex>\RNr[n]</latex>
            </math> is</para.body>
      </para>
      <math.display>
         <latex>\omega_i\ =\ \arccos \frac{x_i}{| \mathbf{x} |}</latex>
      </math.display>
   </statement.theorem>
   <proof>
      <proof.block>
         <para>
            <para.body>To see where this identity comes from, recall that <math>
                  <latex>\mathbf{e}_i</latex>
               </math> has length <math>
                  <latex>1</latex>
               </math>; i.e. <math>
                  <latex>| \mathbf{e}_i | = 1</latex>
               </math>. Then we compute</para.body>
         </para>
         <math.display>
            <latex>x_i = \mathbf{e}_i \bullet \mathbf{x} = | \mathbf{e}_i | | \mathbf{x} | \cos \omega_i = | \mathbf{x} | \cos \omega_i</latex>
         </math.display>
         <para>
            <para.body>This implies the claim.</para.body>
         </para>
      </proof.block>
   </proof>
</theorem>
