<?xml version="1.0"?>
<unit tagname="Lecture" unitid="1" standalone="false">
  <description>Unit1</description>
  <titles>
    <title>Unit 1</title>
    <plain.title>Unit1</plain.title>
  </titles>
  <dates>
    <creation>
      <date>
        <month>05</month>
        <day>30</day>
        <year>2013</year>
      </date>
    </creation>
    <last.revision>
      <date>
        <month>05</month>
        <day>30</day>
        <year>2013</year>
      </date>
    </last.revision>
  </dates>
  <body>
    <block>
      <block.body>
        <def type="Notation" id="2">
          <caption>def1</caption>
          <description>fdsfdf</description>
          <def.body>
            <para align="left">
              <para.body>def1</para.body>
            </para>
          </def.body>
          <associate type="Comment">
            <info>
              <info.caption>
                <para align="left">
                  <para.body>associate 1</para.body>
                </para>
              </info.caption>
              <para align="left">
                <para.body>assocaite content</para.body>
              </para>
            </info>
          </associate>
        </def>
      </block.body>
    </block>
  </body>
  <legitimate.children>
    <unit.choice unitId="5"/>
  </legitimate.children>
</unit>
